repoupdate.py
repoupdate-0.1.0.dist-info/entry_points.txt
repoupdate-0.1.0.dist-info/LICENSE
repoupdate-0.1.0.dist-info/WHEEL
repoupdate-0.1.0.dist-info/METADATA
repoupdate-0.1.0.dist-info/RECORD
