Metadata-Version: 2.1
Name: repoupdate
Version: 0.1.0
Summary: Sync your local with remote
License: GPL-3.0
Author: Jiri Podivin
Author-email: jpodivin@redhat.com
Requires-Python: >=3.9
Classifier: License :: OSI Approved :: GNU General Public License v3 (GPLv3)
Classifier: Programming Language :: Python :: 3
Classifier: Programming Language :: Python :: 3.9
Classifier: Programming Language :: Python :: 3.10
